README.md
setup.cfg
setup.py
lumber_cloud/__init__.py
lumber_cloud.egg-info/PKG-INFO
lumber_cloud.egg-info/SOURCES.txt
lumber_cloud.egg-info/dependency_links.txt
lumber_cloud.egg-info/requires.txt
lumber_cloud.egg-info/top_level.txt
lumber_cloud/helpers/__init__.py
lumber_cloud/helpers/trace.py
lumber_cloud/models/Lumber.py
lumber_cloud/models/__init__.py